mynx/__init__.py
mynx/data_loader.py
mynx/logs.py
mynx/model.py
mynx/callbacks/__init__.py
mynx/callbacks/callback.py
mynx/callbacks/check_point.py
mynx/callbacks/metrics/__init__.py
mynx/callbacks/metrics/epoch_couter.py
mynx/callbacks/metrics/loading.py
mynx/callbacks/metrics/loss.py
mynx/callbacks/metrics/step_counter.py
mynx/callbacks/metrics/time_tracing.py
mynx/modules/__init__.py
mynx/modules/seq/__init__.py
mynx/modules/seq/attention.py
mynx/src/__init__.py
mynx/src/cycle.py
mynx-0.13.0.dist-info/METADATA
mynx-0.13.0.dist-info/WHEEL
mynx-0.13.0.dist-info/top_level.txt
mynx-0.13.0.dist-info/RECORD
