Metadata-Version: 2.4
Name: mynx
Version: 0.13.0
Summary: Add your description here
Requires-Python: >=3.13
Requires-Dist: einops>=0.8.1
Requires-Dist: flax>=0.10.6
Requires-Dist: jax[cuda12]>=0.6.2
